phonochrome.py
phonochrome-1.0.0.dist-info/LICENSE
phonochrome-1.0.0.dist-info/METADATA
phonochrome-1.0.0.dist-info/WHEEL
phonochrome-1.0.0.dist-info/entry_points.txt
phonochrome-1.0.0.dist-info/top_level.txt
phonochrome-1.0.0.dist-info/RECORD
