Metadata-Version: 2.1
Name: phonochrome
Version: 1.0.0
Summary: A bijective 8-bit RGB encoding library that generates phonotactically plausible appellations.
Home-page: https://github.com/Kreusada/Phonochrome
Author: Kreusada
Author-email: kreusadaprojects@gmail.com
Keywords: RGB encoding,linguistics,phonotactics,bijective,encoding
Classifier: Programming Language :: Python
Classifier: Programming Language :: Python :: 3
Classifier: Programming Language :: Python :: 3.5
Classifier: Programming Language :: Python :: 3.6
Classifier: Programming Language :: Python :: 3.7
Classifier: Programming Language :: Python :: 3.8
Classifier: Programming Language :: Python :: 3.9
Classifier: Programming Language :: Python :: 3.10
Classifier: Programming Language :: Python :: Implementation :: CPython
Classifier: Intended Audience :: Developers
Classifier: License :: OSI Approved :: MIT License
Classifier: Operating System :: OS Independent
Classifier: Topic :: Text Processing :: Linguistic
Classifier: Topic :: Scientific/Engineering :: Information Analysis
Classifier: Topic :: Utilities
Classifier: Development Status :: 4 - Beta
Requires-Python: >=3.5
License-File: LICENSE
